appimage/__init__.py
appimage/__main__.py
appimage/appstarter.py
appimage-1.0.0.dist-info/METADATA
appimage-1.0.0.dist-info/WHEEL
appimage-1.0.0.dist-info/licenses/LICENSE
appimage-1.0.0.dist-info/RECORD
