Metadata-Version: 2.3
Name: appimage
Version: 1.0.0
Dynamic: Requires-Dist
Summary: AppImage start script to convert the python application in full python environment
Project-URL: Homepage, https://www.ssh-mitm.at
Project-URL: Documentation, https://appimage.ssh-mitm.at
Project-URL: Changelog, https://github.com/ssh-mitm/appimage/blob/master/CHANGELOG.md
Project-URL: Source, https://github.com/ssh-mitm/appimage
Project-URL: Tracker, https://github.com/ssh-mitm/appimage/issues
Author-email: SSH-MITM Dev-Team <support@ssh-mitm.at>
Maintainer-email: Manfred Kaiser <manfred.kaiser@ssh-mitm.at>
License:                     GNU GENERAL PUBLIC LICENSE
License-File: LICENSE
Keywords: appimage
Classifier: Development Status :: 5 - Production/Stable
Classifier: License :: OSI Approved :: GNU General Public License v3 (GPLv3)
Classifier: Programming Language :: Python :: 3
Classifier: Programming Language :: Python :: 3.8
Classifier: Programming Language :: Python :: 3.9
Classifier: Programming Language :: Python :: 3.10
Classifier: Programming Language :: Python :: 3.11
Classifier: Topic :: System :: Networking
Requires-Python: >=3.8
